smartmin/__init__.py
smartmin/apps.py
smartmin/backends.py
smartmin/email.py
smartmin/middleware.py
smartmin/mixins.py
smartmin/models.py
smartmin/pdf.py
smartmin/perms.py
smartmin/tests.py
smartmin/views.py
smartmin/widgets.py
smartmin/management/__init__.py
smartmin/management/tests.py
smartmin/management/commands/__init__.py
smartmin/management/commands/collect_sql.py
smartmin/management/commands/migrate_manual.py
smartmin/static/top.png
smartmin/static/css/bootstrap-datepicker3.css
smartmin/static/css/bootstrap-theme.css
smartmin/static/css/bootstrap.css
smartmin/static/css/smartmin_styles.css
smartmin/static/css/styles.css
smartmin/static/fonts/glyphicons-halflings-regular.eot
smartmin/static/fonts/glyphicons-halflings-regular.svg
smartmin/static/fonts/glyphicons-halflings-regular.ttf
smartmin/static/fonts/glyphicons-halflings-regular.woff
smartmin/static/fonts/glyphicons-halflings-regular.woff2
smartmin/static/img/active.png
smartmin/static/img/background.jpg
smartmin/static/img/button.png
smartmin/static/img/check.png
smartmin/static/img/glyphicons-halflings-white.png
smartmin/static/img/glyphicons-halflings.png
smartmin/static/img/in.png
smartmin/static/img/loc.png
smartmin/static/img/nyaruka.png
smartmin/static/img/out.png
smartmin/static/img/smartmin.png
smartmin/static/img/sort.gif
smartmin/static/img/sort.png
smartmin/static/img/sort_asc.png
smartmin/static/img/sort_dsc.png
smartmin/static/img/smartmin/arrow-down.gif
smartmin/static/img/smartmin/arrow-up.gif
smartmin/static/img/smartmin/changelist-bg.gif
smartmin/static/img/smartmin/changelist-bg_rtl.gif
smartmin/static/img/smartmin/chooser-bg.gif
smartmin/static/img/smartmin/chooser_stacked-bg.gif
smartmin/static/img/smartmin/default-bg-reverse.gif
smartmin/static/img/smartmin/default-bg.gif
smartmin/static/img/smartmin/deleted-overlay.gif
smartmin/static/img/smartmin/icon-no.gif
smartmin/static/img/smartmin/icon-unknown.gif
smartmin/static/img/smartmin/icon-yes.gif
smartmin-5.2.4.dist-info/METADATA
smartmin-5.2.4.dist-info/WHEEL
smartmin-5.2.4.dist-info/licenses/LICENSE
smartmin-5.2.4.dist-info/RECORD
