Metadata-Version: 2.4
Name: smartmin
Version: 5.2.4
Summary: Scaffolding system for Django object management.
Project-URL: repository, http://github.com/nyaruka/smartmin
Author-email: TextIt <code@textit.com>
License: BSD
License-File: LICENSE
Classifier: Development Status :: 5 - Production/Stable
Classifier: Environment :: Web Environment
Classifier: Framework :: Django
Classifier: Intended Audience :: Developers
Classifier: License :: OSI Approved :: BSD License
Classifier: Operating System :: OS Independent
Classifier: Programming Language :: Python
Requires-Python: <4.0,>=3.11
Requires-Dist: django<5.3,>=5.1.15
Requires-Dist: sqlparse<0.6.0,>=0.4.1
Requires-Dist: xlrd>=1.2.0
Requires-Dist: xlwt>=1.3.0
Provides-Extra: dev
Requires-Dist: black>=24.3.0; extra == 'dev'
Requires-Dist: celery>=5.1.0; extra == 'dev'
Requires-Dist: colorama>=0.4.6; extra == 'dev'
Requires-Dist: coverage[toml]>=7.2.7; extra == 'dev'
Requires-Dist: funcsigs>=1.0.2; extra == 'dev'
Requires-Dist: isort>=5.12.0; extra == 'dev'
Requires-Dist: pillow>=10.3.0; extra == 'dev'
Requires-Dist: psycopg2-binary>=2.9.1; extra == 'dev'
Requires-Dist: redis>=3.5.3; extra == 'dev'
Requires-Dist: ruff>=0.0.278; extra == 'dev'
